{
    "resultados": [],
    "paginaAtual": 0,
    "nomeTela": "Lote",
    "actionsHeader": [{
        "isDownload": false,
        "title": "Clique para criar um novo registro.",
        "download": false,
        "descricao": "Novo",
        "icone": "ui-icon-plus",
        "href": "../novo/"
    }],
    "totalRegistros": 152983,
    "totalizadores": {},
    "chave": "LOTE",
    "pesquisaveis": [
        {
            "valorOrdenacao": null,
            "valorPadrao": "",
            "tipoAlinhamento": "ESQUERDA",
            "tipoEnum": null,
            "operacaoPadrao": "LIKE",
            "valor": "l.codigolote",
            "tipo": "STRING",
            "criadoEm": 28110264072700,
            "dinamico": false,
            "tipoOrdenacao": null,
            "obrigatorio": false,
            "descricao": "Lote (Município)",
            "totalizar": false
        },
        {
            "valorOrdenacao": null,
            "valorPadrao": "",
            "tipoAlinhamento": "ESQUERDA",
            "tipoEnum": null,
            "operacaoPadrao": "LIKE",
            "valor": "s_lote.codigo",
            "tipo": "STRING",
            "criadoEm": 28111187736500,
            "dinamico": false,
            "tipoOrdenacao": null,
            "obrigatorio": false,
            "descricao": "Código do Setor do Lote",
            "totalizar": false
        },
        {
            "valorOrdenacao": null,
            "valorPadrao": "",
            "tipoAlinhamento": "ESQUERDA",
            "tipoEnum": null,
            "operacaoPadrao": "LIKE",
            "valor": "s_lote.nome",
            "tipo": "STRING",
            "criadoEm": 24963761175958,
            "dinamico": false,
            "tipoOrdenacao": null,
            "obrigatorio": false,
            "descricao": "Nome do Setor do Lote",
            "totalizar": false
        },
        {
            "valorOrdenacao": null,
            "valorPadrao": "",
            "tipoAlinhamento": "ESQUERDA",
            "tipoEnum": null,
            "operacaoPadrao": "LIKE",
            "valor": "d.codigo",
            "tipo": "STRING",
            "criadoEm": 12518519340403,
            "dinamico": false,
            "tipoOrdenacao": null,
            "obrigatorio": false,
            "descricao": "Código do Distrito do Setor do Lote",
            "totalizar": false
        },
        {
            "valorOrdenacao": null,
            "valorPadrao": "",
            "tipoAlinhamento": "ESQUERDA",
            "tipoEnum": null,
            "operacaoPadrao": "LIKE",
            "valor": "d.nome",
            "tipo": "STRING",
            "criadoEm": 25029721542432,
            "dinamico": false,
            "tipoOrdenacao": null,
            "obrigatorio": false,
            "descricao": "Nome do Distrito do Setor do Lote",
            "totalizar": false
        },
        {
            "valorOrdenacao": null,
            "valorPadrao": "",
            "tipoAlinhamento": "ESQUERDA",
            "tipoEnum": null,
            "operacaoPadrao": "LIKE",
            "valor": "s_quadra.codigo",
            "tipo": "STRING",
            "criadoEm": 25395438270177,
            "dinamico": false,
            "tipoOrdenacao": null,
            "obrigatorio": false,
            "descricao": "Código do Setor da Quadra",
            "totalizar": false
        },
        {
            "valorOrdenacao": null,
            "valorPadrao": "",
            "tipoAlinhamento": "ESQUERDA",
            "tipoEnum": null,
            "operacaoPadrao": "LIKE",
            "valor": "s_quadra.nome",
            "tipo": "STRING",
            "criadoEm": 12720097297407,
            "dinamico": false,
            "tipoOrdenacao": null,
            "obrigatorio": false,
            "descricao": "Nome do Setor da Quadra",
            "totalizar": false
        },
        {
            "valorOrdenacao": null,
            "valorPadrao": "",
            "tipoAlinhamento": "ESQUERDA",
            "tipoEnum": null,
            "operacaoPadrao": "LIKE",
            "valor": "q.codigo",
            "tipo": "STRING",
            "criadoEm": 28111786968100,
            "dinamico": false,
            "tipoOrdenacao": null,
            "obrigatorio": false,
            "descricao": "Número da quadra",
            "totalizar": false
        },
        {
            "valorOrdenacao": null,
            "valorPadrao": "",
            "tipoAlinhamento": "ESQUERDA",
            "tipoEnum": null,
            "operacaoPadrao": "LIKE",
            "valor": "q.descricao",
            "tipo": "STRING",
            "criadoEm": 28112600218100,
            "dinamico": false,
            "tipoOrdenacao": null,
            "obrigatorio": false,
            "descricao": "Descrição da Quadra (Municipio)",
            "totalizar": false
        },
        {
            "valorOrdenacao": null,
            "valorPadrao": "",
            "tipoAlinhamento": "ESQUERDA",
            "tipoEnum": null,
            "operacaoPadrao": "IGUAL",
            "valor": "lt.codigo",
            "tipo": "INTEGER",
            "criadoEm": 28113177729500,
            "dinamico": false,
            "tipoOrdenacao": null,
            "obrigatorio": false,
            "descricao": "Código do Loteamento da Quadra",
            "totalizar": false
        },
        {
            "valorOrdenacao": null,
            "valorPadrao": "",
            "tipoAlinhamento": "ESQUERDA",
            "tipoEnum": null,
            "operacaoPadrao": "LIKE",
            "valor": "lt.nome",
            "tipo": "STRING",
            "criadoEm": 28114534193000,
            "dinamico": false,
            "tipoOrdenacao": null,
            "obrigatorio": false,
            "descricao": "Nome do Loteamento da Quadra",
            "totalizar": false
        },
        {
            "valorOrdenacao": null,
            "valorPadrao": "",
            "tipoAlinhamento": "ESQUERDA",
            "tipoEnum": null,
            "operacaoPadrao": "LIKE",
            "valor": "q.descricaoloteamento",
            "tipo": "STRING",
            "criadoEm": 28113860088500,
            "dinamico": false,
            "tipoOrdenacao": null,
            "obrigatorio": false,
            "descricao": "Descrição do Loteamento da Quadra",
            "totalizar": false
        },
        {
            "valorOrdenacao": null,
            "valorPadrao": "",
            "tipoAlinhamento": "ESQUERDA",
            "tipoEnum": null,
            "operacaoPadrao": "LIKE",
            "valor": "l.descricaoLoteamento",
            "tipo": "STRING",
            "criadoEm": 12847533836982,
            "dinamico": false,
            "tipoOrdenacao": null,
            "obrigatorio": false,
            "descricao": "Lote (Loteamento)",
            "totalizar": false
        },
        {
            "valorOrdenacao": null,
            "valorPadrao": 0,
            "tipoAlinhamento": "ESQUERDA",
            "tipoEnum": null,
            "operacaoPadrao": "IGUAL",
            "valor": "l.arealote",
            "tipo": "DECIMAL",
            "criadoEm": 28115208295700,
            "dinamico": false,
            "tipoOrdenacao": null,
            "obrigatorio": false,
            "descricao": "Área do Lote",
            "totalizar": false
        },
        {
            "valorOrdenacao": null,
            "valorPadrao": "",
            "tipoAlinhamento": "ESQUERDA",
            "tipoEnum": null,
            "operacaoPadrao": "LIKE",
            "valor": "l.numerocorreio",
            "tipo": "STRING",
            "criadoEm": 25695567060256,
            "dinamico": false,
            "tipoOrdenacao": null,
            "obrigatorio": false,
            "descricao": "Número",
            "totalizar": false
        },
        {
            "valorOrdenacao": null,
            "valorPadrao": "",
            "tipoAlinhamento": "ESQUERDA",
            "tipoEnum": null,
            "operacaoPadrao": "LIKE",
            "valor": "l.complemento",
            "tipo": "STRING",
            "criadoEm": 28116049090700,
            "dinamico": false,
            "tipoOrdenacao": null,
            "obrigatorio": false,
            "descricao": "Complemento",
            "totalizar": false
        },
        {
            "valorOrdenacao": null,
            "valorPadrao": null,
            "tipoAlinhamento": "ESQUERDA",
            "tipoEnum": "br.com.webpublico.enums.Patrimonio",
            "operacaoPadrao": "IGUAL",
            "valor": "l.patrimonio",
            "tipo": "ENUM",
            "criadoEm": 25549963867337,
            "dinamico": false,
            "tipoOrdenacao": null,
            "obrigatorio": false,
            "descricao": "Patrimônio",
            "totalizar": false
        }
    ],
    "from": "from lote l\r\n         left join setor s_lote on l.SETOR_ID = s_lote.ID\r\n         left join distrito d on s_lote.distrito_id = d.id\r\n         left join quadra q on l.quadra_id = q.id\r\n         left join setor s_quadra on q.SETOR_ID = s_quadra.ID\r\n         left join loteamento lt on q.loteamento_id = lt.id",
    "distinct": false,
    "groupBy": "",
    "registroPorPagina": 10,
    "identificador": {
        "valorOrdenacao": null,
        "valorPadrao": null,
        "tipoAlinhamento": "ESQUERDA",
        "tipoEnum": null,
        "operacaoPadrao": null,
        "valor": "l.id",
        "tipo": null,
        "criadoEm": 28091845176900,
        "dinamico": false,
        "tipoOrdenacao": null,
        "obrigatorio": false,
        "descricao": null,
        "totalizar": false
    },
    "tabelaveis": [
        {
            "valorOrdenacao": "to_number(l.codigolote)",
            "valorPadrao": null,
            "tipoAlinhamento": "ESQUERDA",
            "tipoEnum": null,
            "operacaoPadrao": null,
            "valor": "l.codigolote",
            "tipo": "STRING",
            "criadoEm": 29991140553700,
            "dinamico": false,
            "tipoOrdenacao": null,
            "obrigatorio": false,
            "descricao": "Lote (Município)",
            "totalizar": false
        },
        {
            "valorOrdenacao": "s_lote.CODIGO|| ' - '  || s_lote.NOME",
            "valorPadrao": null,
            "tipoAlinhamento": "ESQUERDA",
            "tipoEnum": null,
            "operacaoPadrao": null,
            "valor": "s_lote.CODIGO|| ' - '  || s_lote.NOME",
            "tipo": "STRING",
            "criadoEm": 25811643482437,
            "dinamico": false,
            "tipoOrdenacao": null,
            "obrigatorio": false,
            "descricao": "Setor",
            "totalizar": false
        },
        {
            "valorOrdenacao": "'Descrição: ' || q.DESCRICAO || ' Cód. Municipal: ' || q.codigo",
            "valorPadrao": null,
            "tipoAlinhamento": "ESQUERDA",
            "tipoEnum": null,
            "operacaoPadrao": null,
            "valor": "'Descrição: ' || q.DESCRICAO || ' Cód. Municipal: ' || q.codigo",
            "tipo": "STRING",
            "criadoEm": 29994741605300,
            "dinamico": false,
            "tipoOrdenacao": null,
            "obrigatorio": false,
            "descricao": "Quadra",
            "totalizar": false
        },
        {
            "valorOrdenacao": "l.descricaoLoteamento",
            "valorPadrao": null,
            "tipoAlinhamento": "ESQUERDA",
            "tipoEnum": null,
            "operacaoPadrao": null,
            "valor": "l.descricaoLoteamento",
            "tipo": "STRING",
            "criadoEm": 30004454853200,
            "dinamico": false,
            "tipoOrdenacao": null,
            "obrigatorio": false,
            "descricao": "Lote (Loteamento)",
            "totalizar": false
        },
        {
            "valorOrdenacao": "to_char(l.arealote, '999999990D99')",
            "valorPadrao": null,
            "tipoAlinhamento": "ESQUERDA",
            "tipoEnum": null,
            "operacaoPadrao": null,
            "valor": "to_char(l.arealote, '999999990D99')",
            "tipo": "STRING",
            "criadoEm": 30007489715900,
            "dinamico": false,
            "tipoOrdenacao": null,
            "obrigatorio": false,
            "descricao": "Área do Lote",
            "totalizar": false
        },
        {
            "valorOrdenacao": "l.numerocorreio",
            "valorPadrao": null,
            "tipoAlinhamento": "ESQUERDA",
            "tipoEnum": null,
            "operacaoPadrao": null,
            "valor": "l.numerocorreio",
            "tipo": "STRING",
            "criadoEm": 25852675895498,
            "dinamico": false,
            "tipoOrdenacao": null,
            "obrigatorio": false,
            "descricao": "Número",
            "totalizar": false
        },
        {
            "valorOrdenacao": "l.complemento",
            "valorPadrao": null,
            "tipoAlinhamento": "ESQUERDA",
            "tipoEnum": null,
            "operacaoPadrao": null,
            "valor": "l.complemento",
            "tipo": "STRING",
            "criadoEm": 30008093254100,
            "dinamico": false,
            "tipoOrdenacao": null,
            "obrigatorio": false,
            "descricao": "Complemento",
            "totalizar": false
        },
        {
            "valorOrdenacao": "(select logra.CODIGO || ' - ' || tl.DESCRICAO || ' ' || logra.NOME from Testada t inner join face f on t.FACE_ID = f.ID inner join logradouroBairro lb on f.LOGRADOUROBAIRRO_ID = lb.ID inner join logradouro logra on lb.LOGRADOURO_ID = logra.ID left join tipologradouro tl on logra.TIPOLOGRADOURO_ID = tl.ID where t.principal = 1 and t.LOTE_ID = l.ID and ROWNUM = 1)",
            "valorPadrao": null,
            "tipoAlinhamento": "ESQUERDA",
            "tipoEnum": null,
            "operacaoPadrao": null,
            "valor": "(select logra.CODIGO || ' - ' || tl.DESCRICAO || ' ' || logra.NOME from Testada t inner join face f on t.FACE_ID = f.ID inner join logradouroBairro lb on f.LOGRADOUROBAIRRO_ID = lb.ID inner join logradouro logra on lb.LOGRADOURO_ID = logra.ID left join tipologradouro tl on logra.TIPOLOGRADOURO_ID = tl.ID where t.principal = 1 and t.LOTE_ID = l.ID and ROWNUM = 1)",
            "tipo": "STRING",
            "criadoEm": 25896839425638,
            "dinamico": false,
            "tipoOrdenacao": null,
            "obrigatorio": false,
            "descricao": "Logradouro Principal",
            "totalizar": false
        }
    ],
    "actionsTabela": [
        {
            "isDownload": false,
            "title": "Clique para visualizar este registro.",
            "download": false,
            "descricao": null,
            "icone": "ui-icon-search",
            "href": "../ver/$identificador/"
        },
        {
            "isDownload": false,
            "title": "Clique para editar este registro.",
            "download": false,
            "descricao": null,
            "icone": "ui-icon-pencil",
            "href": "../editar/$identificador/"
        }
    ],
    "filtros": []
}