{
  "totalizadores": {},
  "paginaAtual": 0,
  "pesquisaveis": [
    {
      "tipo": "INTEGER",
      "dinamico": false,
      "select": null,
      "obrigatorio": false,
      "tipoEnum": null,
      "totalizar": false,
      "valor": "pca.numero",
      "tipoOrdenacao": null,
      "operacaoPadrao": null,
      "valorOrdenacao": "pac.numero",
      "descricao": "Número",
      "tipoAlinhamento": "ESQUERDA",
      "criadoEm": 26766267378025,
      "ordem": 1,
      "valorPadrao": ""
    },
    {
      "tipo": "INTEGER",
      "dinamico": false,
      "select": null,
      "obrigatorio": false,
      "tipoEnum": null,
      "totalizar": false,
      "valor": "ex.ano",
      "tipoOrdenacao": null,
      "operacaoPadrao": null,
      "valorOrdenacao": "ex.ano",
      "descricao": "Ano de Aplicação",
      "tipoAlinhamento": "ESQUERDA",
      "criadoEm": 26768835497161,
      "ordem": 2,
      "valorPadrao": ""
    },
    {
      "tipo": "DATE",
      "dinamico": false,
      "select": null,
      "obrigatorio": false,
      "tipoEnum": null,
      "totalizar": false,
      "valor": "pca.inicioelaboracao",
      "tipoOrdenacao": null,
      "operacaoPadrao": null,
      "valorOrdenacao": "pac.inicioelaboracao",
      "descricao": "Início da Elaboração",
      "tipoAlinhamento": "ESQUERDA",
      "criadoEm": 26770830751449,
      "ordem": 3,
      "valorPadrao": null
    },
    {
      "tipo": "DATE",
      "dinamico": false,
      "select": null,
      "obrigatorio": false,
      "tipoEnum": null,
      "totalizar": false,
      "valor": "pca.fimelaboracao",
      "tipoOrdenacao": null,
      "operacaoPadrao": null,
      "valorOrdenacao": "pac.fimelaboracao",
      "descricao": "Fim da Elaboração",
      "tipoAlinhamento": "ESQUERDA",
      "criadoEm": 26772055934350,
      "ordem": 4,
      "valorPadrao": null
    },
    {
      "tipo": "STRING",
      "dinamico": false,
      "select": null,
      "obrigatorio": false,
      "tipoEnum": null,
      "totalizar": false,
      "valor": "vw.codigo",
      "tipoOrdenacao": null,
      "operacaoPadrao": null,
      "valorOrdenacao": "vw.codigo ||  ' - ' || vw.descricao",
      "descricao": "Unidade Organizacional.Código",
      "tipoAlinhamento": "ESQUERDA",
      "criadoEm": 26773372191768,
      "ordem": 5,
      "valorPadrao": ""
    },
    {
      "tipo": "STRING",
      "dinamico": false,
      "select": null,
      "obrigatorio": false,
      "tipoEnum": null,
      "totalizar": false,
      "valor": "vw.descricao",
      "tipoOrdenacao": null,
      "operacaoPadrao": null,
      "valorOrdenacao": null,
      "descricao": "Unidade Organizacional.Descrição",
      "tipoAlinhamento": "ESQUERDA",
      "criadoEm": 26781272455179,
      "ordem": 6,
      "valorPadrao": ""
    },
    {
      "tipo": "STRING",
      "dinamico": false,
      "select": null,
      "obrigatorio": false,
      "tipoEnum": null,
      "totalizar": false,
      "valor": "ato.numero",
      "tipoOrdenacao": null,
      "operacaoPadrao": null,
      "valorOrdenacao": null,
      "descricao": "Ato Legal.Número",
      "tipoAlinhamento": "ESQUERDA",
      "criadoEm": 26917849500527,
      "ordem": 7,
      "valorPadrao": ""
    },
    {
      "tipo": "STRING",
      "dinamico": false,
      "select": null,
      "obrigatorio": false,
      "tipoEnum": null,
      "totalizar": false,
      "valor": "ato.nome",
      "tipoOrdenacao": null,
      "operacaoPadrao": null,
      "valorOrdenacao": null,
      "descricao": "Ato Legal.Nome",
      "tipoAlinhamento": "ESQUERDA",
      "criadoEm": 26943035374655,
      "ordem": 8,
      "valorPadrao": ""
    },
    {
      "tipo": "STRING",
      "dinamico": false,
      "select": null,
      "obrigatorio": false,
      "tipoEnum": null,
      "totalizar": false,
      "valor": "goc.codigo",
      "tipoOrdenacao": null,
      "operacaoPadrao": null,
      "valorOrdenacao": null,
      "descricao": "Grupo Objeto de Compra.Código",
      "tipoAlinhamento": "ESQUERDA",
      "criadoEm": 26998493447630,
      "ordem": 9,
      "valorPadrao": ""
    },
    {
      "tipo": "STRING",
      "dinamico": false,
      "select": null,
      "obrigatorio": false,
      "tipoEnum": null,
      "totalizar": false,
      "valor": "goc.descricao",
      "tipoOrdenacao": null,
      "operacaoPadrao": null,
      "valorOrdenacao": null,
      "descricao": "Grupo Objeto de Compra.Descrição",
      "tipoAlinhamento": "ESQUERDA",
      "criadoEm": 27021147880843,
      "ordem": 10,
      "valorPadrao": ""
    },
    {
      "tipo": "INTEGER",
      "dinamico": false,
      "select": null,
      "obrigatorio": false,
      "tipoEnum": null,
      "totalizar": false,
      "valor": "oc.codigo",
      "tipoOrdenacao": null,
      "operacaoPadrao": null,
      "valorOrdenacao": null,
      "descricao": "Objeto de Compra.Código",
      "tipoAlinhamento": "ESQUERDA",
      "criadoEm": 27037422500667,
      "ordem": 11,
      "valorPadrao": ""
    },
    {
      "tipo": "STRING",
      "dinamico": false,
      "select": null,
      "obrigatorio": false,
      "tipoEnum": null,
      "totalizar": false,
      "valor": "oc.descricao",
      "tipoOrdenacao": null,
      "operacaoPadrao": null,
      "valorOrdenacao": null,
      "descricao": "Objeto de Compra.Descrição",
      "tipoAlinhamento": "ESQUERDA",
      "criadoEm": 27058996657814,
      "ordem": 12,
      "valorPadrao": ""
    }
  ],
  "actionsHeader": [{
    "isDownload": false,
    "download": false,
    "icone": "ui-icon-plus",
    "style": "",
    "href": "../novo/",
    "title": "Clique para criar um novo registro.",
    "alinhamento": "ESQUERDA",
    "descricao": "Novo"
  }],
  "chave": "PLANO_CONTRATACAO_ANUAL",
  "distinct": true,
  "tabelaveis": [
    {
      "tipo": "INTEGER",
      "dinamico": false,
      "select": null,
      "obrigatorio": false,
      "tipoEnum": null,
      "totalizar": false,
      "valor": "pca.numero",
      "tipoOrdenacao": null,
      "operacaoPadrao": null,
      "valorOrdenacao": "pca.numero",
      "descricao": "Número",
      "tipoAlinhamento": "ESQUERDA",
      "criadoEm": 12082758265394,
      "ordem": 0,
      "valorPadrao": null
    },
    {
      "tipo": "INTEGER",
      "dinamico": false,
      "select": null,
      "obrigatorio": false,
      "tipoEnum": null,
      "totalizar": false,
      "valor": "ex.ano",
      "tipoOrdenacao": null,
      "operacaoPadrao": null,
      "valorOrdenacao": "ex.ano",
      "descricao": "Ano de Aplicação",
      "tipoAlinhamento": "ESQUERDA",
      "criadoEm": 26698877109945,
      "ordem": 4,
      "valorPadrao": null
    },
    {
      "tipo": "DATE",
      "dinamico": false,
      "select": null,
      "obrigatorio": false,
      "tipoEnum": null,
      "totalizar": false,
      "valor": "pca.inicioelaboracao",
      "tipoOrdenacao": null,
      "operacaoPadrao": null,
      "valorOrdenacao": "pca.inicioelaboracao",
      "descricao": "Início da Elaboração",
      "tipoAlinhamento": "ESQUERDA",
      "criadoEm": 26590242087939,
      "ordem": 1,
      "valorPadrao": null
    },
    {
      "tipo": "DATE",
      "dinamico": false,
      "select": null,
      "obrigatorio": false,
      "tipoEnum": null,
      "totalizar": false,
      "valor": "pca.fimelaboracao",
      "tipoOrdenacao": null,
      "operacaoPadrao": null,
      "valorOrdenacao": "pca.fimelaboracao",
      "descricao": "Fim da Elaboração",
      "tipoAlinhamento": "ESQUERDA",
      "criadoEm": 26655124767867,
      "ordem": 2,
      "valorPadrao": null
    },
    {
      "tipo": "STRING",
      "dinamico": false,
      "select": null,
      "obrigatorio": false,
      "tipoEnum": null,
      "totalizar": false,
      "valor": "vw.codigo ||  ' - ' || vw.descricao",
      "tipoOrdenacao": null,
      "operacaoPadrao": null,
      "valorOrdenacao": "vw.codigo ||  ' - ' || vw.descricao",
      "descricao": "Unidade Organizacional",
      "tipoAlinhamento": "ESQUERDA",
      "criadoEm": 26672940178435,
      "ordem": 3,
      "valorPadrao": null
    }
  ],
  "groupBy": "",
  "actionsTabela": [
    {
      "isDownload": false,
      "download": false,
      "icone": "ui-icon-search",
      "style": "",
      "href": "../ver/$identificador/",
      "title": "Clique para visualizar este registro.",
      "alinhamento": "ESQUERDA",
      "descricao": null
    },
    {
      "isDownload": false,
      "download": false,
      "icone": "ui-icon-pencil",
      "style": "",
      "href": "../editar/$identificador/",
      "title": "Clique para editar este registro.",
      "alinhamento": "ESQUERDA",
      "descricao": null
    },
    {
      "isDownload": false,
      "download": false,
      "icone": "ui-icon-clock",
      "style": "",
      "href": "/auditoria/listar-por-entidade/$identificador/PLANO_ANUAL_CONTRATACAO/",
      "title": "Clique para ver o histórico deste registro.",
      "alinhamento": "DIREITA",
      "descricao": null
    }
  ],
  "totalRegistros": 3,
  "nomeTela": "Plano de Contratações Anual - PCA",
  "resultados": [],
  "registroPorPagina": 10,
  "from": "from planocontratacaoanual pca\r\ninner join exercicio ex on ex.id = pca.exercicio_id\r\ninner join vwhierarquiaadministrativa vw on vw.subordinada_id = pca.unidadeorganizacional_id\r\ninner join planocontratanualgrupo pcagoc on pcagoc.planocontratacaoanual_id = pca.id\r\ninner join grupoobjetocompra goc on goc.id = pcagoc.grupoobjetocompra_id\r\nleft join planocontratanualobjcomp pcaoc on pcaoc.planocontratacaoanualgrupo_id = pcagoc.id\r\nleft join objetocompra oc on oc.id = pcaoc.objetocompra_id\r\nleft join atolegal ato on ato.id = pca.atolegal_id\r\nwhere $DATA_OPERACAO between trunc(vw.inicioVigencia) and coalesce(trunc(vw.fimvigencia),$DATA_OPERACAO)",
  "filtros": [],
  "identificador": {
    "tipo": null,
    "dinamico": false,
    "select": null,
    "obrigatorio": false,
    "tipoEnum": null,
    "totalizar": false,
    "valor": "pca.id",
    "tipoOrdenacao": null,
    "operacaoPadrao": null,
    "valorOrdenacao": null,
    "descricao": null,
    "tipoAlinhamento": "ESQUERDA",
    "criadoEm": 12037496653146,
    "ordem": null,
    "valorPadrao": null
  }
}
