{
    "resultados": [],
    "paginaAtual": 0,
    "nomeTela": "Remessa de Protestos",
    "actionsHeader": [{
        "isDownload": false,
        "title": "Clique para criar um novo registro.",
        "style": "",
        "alinhamento": "ESQUERDA",
        "download": false,
        "descricao": "Novo",
        "icone": "ui-icon-plus",
        "href": "../novo/"
    }],
    "totalRegistros": 0,
    "totalizadores": {},
    "chave": "REMESSA_DE_PROTESTO",
    "pesquisaveis": [
        {
            "valorOrdenacao": "remessa.sequencia",
            "valorPadrao": "",
            "tipoAlinhamento": "ESQUERDA",
            "tipoEnum": null,
            "operacaoPadrao": "IGUAL",
            "valor": "remessa.sequencia",
            "tipo": "INTEGER",
            "criadoEm": 2014749890736,
            "dinamico": false,
            "tipoOrdenacao": null,
            "obrigatorio": false,
            "descricao": "Sequência",
            "totalizar": false
        },
        {
            "valorOrdenacao": "remessa.envioremessa",
            "valorPadrao": null,
            "tipoAlinhamento": "ESQUERDA",
            "tipoEnum": null,
            "operacaoPadrao": "IGUAL",
            "valor": "remessa.envioremessa",
            "tipo": "DATE",
            "criadoEm": 2020584301869,
            "dinamico": false,
            "tipoOrdenacao": null,
            "obrigatorio": false,
            "descricao": "Data de Envio",
            "totalizar": false
        },
        {
            "valorOrdenacao": "us.login",
            "valorPadrao": "",
            "tipoAlinhamento": "ESQUERDA",
            "tipoEnum": null,
            "operacaoPadrao": "LIKE",
            "valor": "us.login",
            "tipo": "STRING",
            "criadoEm": 2030716005472,
            "dinamico": false,
            "tipoOrdenacao": null,
            "obrigatorio": false,
            "descricao": "Usuário Responsável",
            "totalizar": false
        },
        {
            "valorOrdenacao": "remessa.situacaoremessa",
            "valorPadrao": null,
            "tipoAlinhamento": "ESQUERDA",
            "tipoEnum": "br.com.webpublico.enums.tributario.SituacaoRemessaProtesto",
            "operacaoPadrao": "IGUAL",
            "valor": "remessa.situacaoremessa",
            "tipo": "ENUM",
            "criadoEm": 2036057735884,
            "dinamico": false,
            "tipoOrdenacao": null,
            "obrigatorio": false,
            "descricao": "Situação",
            "totalizar": false
        }
    ],
    "from": "from remessaprotesto remessa\r\ninner join usuariosistema us on remessa.responsavelremessa_id = us.id",
    "distinct": false,
    "groupBy": "",
    "registroPorPagina": 10,
    "identificador": {
        "valorOrdenacao": null,
        "valorPadrao": null,
        "tipoAlinhamento": "ESQUERDA",
        "tipoEnum": null,
        "operacaoPadrao": null,
        "valor": "remessa.id",
        "tipo": null,
        "criadoEm": 1751745355643,
        "dinamico": false,
        "tipoOrdenacao": null,
        "obrigatorio": false,
        "descricao": null,
        "totalizar": false
    },
    "tabelaveis": [
        {
            "valorOrdenacao": "remessa.sequencia",
            "valorPadrao": null,
            "tipoAlinhamento": "ESQUERDA",
            "tipoEnum": null,
            "operacaoPadrao": null,
            "valor": "remessa.sequencia",
            "tipo": "INTEGER",
            "criadoEm": 1877362534152,
            "dinamico": false,
            "tipoOrdenacao": null,
            "obrigatorio": false,
            "descricao": "Sequência",
            "totalizar": false
        },
        {
            "valorOrdenacao": "remessa.envioremessa",
            "valorPadrao": null,
            "tipoAlinhamento": "ESQUERDA",
            "tipoEnum": null,
            "operacaoPadrao": null,
            "valor": "remessa.envioremessa",
            "tipo": "DATE",
            "criadoEm": 1897539339695,
            "dinamico": false,
            "tipoOrdenacao": null,
            "obrigatorio": false,
            "descricao": "Data de Envio",
            "totalizar": false
        },
        {
            "valorOrdenacao": "us.login",
            "valorPadrao": null,
            "tipoAlinhamento": "ESQUERDA",
            "tipoEnum": null,
            "operacaoPadrao": null,
            "valor": "us.login",
            "tipo": "STRING",
            "criadoEm": 1908887642638,
            "dinamico": false,
            "tipoOrdenacao": null,
            "obrigatorio": false,
            "descricao": "Usuário Responsável",
            "totalizar": false
        },
        {
            "valorOrdenacao": "remessa.situacaoremessa",
            "valorPadrao": null,
            "tipoAlinhamento": "ESQUERDA",
            "tipoEnum": "br.com.webpublico.enums.tributario.SituacaoRemessaProtesto",
            "operacaoPadrao": null,
            "valor": "remessa.situacaoremessa",
            "tipo": "ENUM",
            "criadoEm": 1959834801784,
            "dinamico": false,
            "tipoOrdenacao": null,
            "obrigatorio": false,
            "descricao": "Situação",
            "totalizar": false
        }
    ],
    "actionsTabela": [
        {
            "isDownload": false,
            "title": "Clique para visualizar este registro.",
            "style": "",
            "alinhamento": "ESQUERDA",
            "download": false,
            "descricao": null,
            "icone": "ui-icon-search",
            "href": "../ver/$identificador/"
        },
        {
            "isDownload": false,
            "title": "Clique para ver o histórico deste registro.",
            "style": "",
            "alinhamento": "DIREITA",
            "download": false,
            "descricao": null,
            "icone": "ui-icon-clock",
            "href": "/auditoria/listar-por-entidade/$identificador/REMESSAPROTESTO/"
        }
    ],
    "filtros": []
}