{
    "resultados": [],
    "paginaAtual": 0,
    "nomeTela": "Solicitação de Estorno de Transferência de Bens Imóveis",
    "actionsHeader": [{
        "isDownload": false,
        "title": "Clique para criar um novo registro.",
        "alinhamento": "ESQUERDA",
        "download": false,
        "descricao": "Novo",
        "icone": "ui-icon-plus",
        "href": "../novo/"
    }],
    "totalRegistros": 0,
    "totalizadores": {},
    "chave": "SOLICITACAO_ESTORNO_TRANSFERENCIA_IMOVEL",
    "pesquisaveis": [
        {
            "valorOrdenacao": "obj.CODIGO",
            "valorPadrao": "",
            "tipoAlinhamento": "ESQUERDA",
            "tipoEnum": null,
            "operacaoPadrao": null,
            "valor": "obj.CODIGO",
            "tipo": "INTEGER",
            "criadoEm": 21517246017088,
            "dinamico": false,
            "tipoOrdenacao": null,
            "obrigatorio": false,
            "descricao": "Solicitação de Estorno de Transferência de Bens Imóveis.Código",
            "totalizar": false
        },
        {
            "valorOrdenacao": "obj.DATADECRIACAO",
            "valorPadrao": null,
            "tipoAlinhamento": "ESQUERDA",
            "tipoEnum": null,
            "operacaoPadrao": null,
            "valor": "obj.DATADECRIACAO",
            "tipo": "DATE",
            "criadoEm": 21519067243032,
            "dinamico": false,
            "tipoOrdenacao": null,
            "obrigatorio": false,
            "descricao": "Solicitação de Estorno de Transferência de Bens Imóveis.Data de criação",
            "totalizar": false
        },
        {
            "valorOrdenacao": "coalesce(pf.NOME, us.LOGIN)",
            "valorPadrao": "",
            "tipoAlinhamento": "ESQUERDA",
            "tipoEnum": null,
            "operacaoPadrao": null,
            "valor": "coalesce(pf.NOME, us.LOGIN)",
            "tipo": "STRING",
            "criadoEm": 21521050119417,
            "dinamico": false,
            "tipoOrdenacao": null,
            "obrigatorio": false,
            "descricao": "Solicitação de Estorno de Transferência de Bens Imóveis.Solicitante",
            "totalizar": false
        },
        {
            "valorOrdenacao": "obj.SITUACAO",
            "valorPadrao": null,
            "tipoAlinhamento": "ESQUERDA",
            "tipoEnum": "br.com.webpublico.enums.SituacaoEventoBem",
            "operacaoPadrao": null,
            "valor": "obj.SITUACAO",
            "tipo": "ENUM",
            "criadoEm": 21523598184616,
            "dinamico": false,
            "tipoOrdenacao": null,
            "obrigatorio": false,
            "descricao": "Solicitação de Estorno de Transferência de Bens Imóveis.Situação",
            "totalizar": false
        },
        {
            "valorOrdenacao": null,
            "valorPadrao": "",
            "tipoAlinhamento": "ESQUERDA",
            "tipoEnum": null,
            "operacaoPadrao": null,
            "valor": "letb.CODIGO",
            "tipo": "INTEGER",
            "criadoEm": 21542640574549,
            "dinamico": false,
            "tipoOrdenacao": null,
            "obrigatorio": false,
            "descricao": "Efetivação de Transferência.Código",
            "totalizar": false
        },
        {
            "valorOrdenacao": null,
            "valorPadrao": "",
            "tipoAlinhamento": "ESQUERDA",
            "tipoEnum": null,
            "operacaoPadrao": null,
            "valor": "coalesce(pfLteb.NOME, usLetb.LOGIN)",
            "tipo": "STRING",
            "criadoEm": 21582260838921,
            "dinamico": false,
            "tipoOrdenacao": null,
            "obrigatorio": false,
            "descricao": "Efetivação de Transferência.Responsável",
            "totalizar": false
        },
        {
            "valorOrdenacao": null,
            "valorPadrao": null,
            "tipoAlinhamento": "ESQUERDA",
            "tipoEnum": null,
            "operacaoPadrao": null,
            "valor": "letb.DATAEFETIVACAO",
            "tipo": "DATE",
            "criadoEm": 21593580396681,
            "dinamico": false,
            "tipoOrdenacao": null,
            "obrigatorio": false,
            "descricao": "Efetivação de Transferência.Data da Efetivação",
            "totalizar": false
        },
        {
            "valorOrdenacao": null,
            "valorPadrao": "",
            "tipoAlinhamento": "ESQUERDA",
            "tipoEnum": null,
            "operacaoPadrao": null,
            "valor": "vwAdm.codigo",
            "tipo": "STRING",
            "criadoEm": 21641749553858,
            "dinamico": false,
            "tipoOrdenacao": null,
            "obrigatorio": false,
            "descricao": "Unidade Administrativa.Código",
            "totalizar": false
        },
        {
            "valorOrdenacao": null,
            "valorPadrao": "",
            "tipoAlinhamento": "ESQUERDA",
            "tipoEnum": null,
            "operacaoPadrao": null,
            "valor": "vwAdm.descricao",
            "tipo": "STRING",
            "criadoEm": 21648257620001,
            "dinamico": false,
            "tipoOrdenacao": null,
            "obrigatorio": false,
            "descricao": "Unidade Administrativa.Descrição",
            "totalizar": false
        }
    ],
    "from": "from SOLICITESTORNOTRANSFER obj\r\n  left join USUARIOSISTEMA us ON us.ID = OBJ.SOLICITANTE_ID\r\n  left join PESSOAFISICA pf on pf.id = us.pessoafisica_id\r\n  inner join LOTEEFETTRANSFBEM letb on letb.ID = obj.LOTEEFETIVACAOTRANSFERENCIA_ID\r\n  left join USUARIOSISTEMA usLetb ON usLetb.ID = letb.USUARIOSISTEMA_ID\r\n  left join PESSOAFISICA pfLteb on pfLteb.id = usLetb.pessoafisica_id\r\n  inner JOIN VWHIERARQUIAADMINISTRATIVA vwAdm ON vwAdm.SUBORDINADA_ID = letb.unidadeOrganizacional_id\r\nwhere trunc(letb.dataEfetivacao) BETWEEN vwAdm.inicioVigencia AND coalesce(vwAdm.fimVigencia, trunc(letb.dataEfetivacao))\r\n      and letb.TIPOBEM = 'IMOVEIS'\r\n      and obj.removido = 0\r\n      and letb.unidadeOrganizacional_id in (\r\n  with dados(id, superior_id, subordinada_id, codigo, descricao ) as (\r\n    select\r\n      vw.id,\r\n      vw.superior_id,\r\n      vw.subordinada_id,\r\n      vw.codigo,\r\n      vw.descricao\r\n    from vwhierarquiaadministrativa vw\r\n    where $DATA_OPERACAO between vw.iniciovigencia and coalesce (vw.fimvigencia, $DATA_OPERACAO)\r\n          AND nivelestrutura(vw.codigo, '.') = 2\r\n          and substr(vw.codigo, 1, 6) in ( select substr(ho.codigo, 1, 6)\r\n                                           from usuariosistema us\r\n                                             inner join usuariounidadeorganizacio uu on uu.usuariosistema_id = us.id\r\n                                             inner join hierarquiaorganizacional ho on ho.subordinada_id = uu.unidadeorganizacional_id\r\n                                           where us.id = $USUARIO_ID\r\n                                             and $DATA_OPERACAO between trunc(ho.iniciovigencia) and coalesce (trunc(ho.fimvigencia), $DATA_OPERACAO)\r\n                                             and uu.gestorpatrimonio = 1)\r\n    UNION ALL\r\n    select vw.id, vw.superior_id, vw.subordinada_id, vw.codigo, vw.descricao\r\n    from vwhierarquiaadministrativa vw\r\n      inner join dados dd on dd.subordinada_id = vw.superior_id\r\n    where $DATA_OPERACAO between vw.iniciovigencia and coalesce (vw.fimvigencia, $DATA_OPERACAO)\r\n  )\r\n  select distinct dd.SUBORDINADA_ID\r\n  from dados dd\r\n)",
    "distinct": false,
    "groupBy": "",
    "registroPorPagina": 10,
    "identificador": {
        "valorOrdenacao": null,
        "valorPadrao": null,
        "tipoAlinhamento": "ESQUERDA",
        "tipoEnum": null,
        "operacaoPadrao": null,
        "valor": "obj.id",
        "tipo": null,
        "criadoEm": 20851836430745,
        "dinamico": false,
        "tipoOrdenacao": null,
        "obrigatorio": false,
        "descricao": null,
        "totalizar": false
    },
    "tabelaveis": [
        {
            "valorOrdenacao": "obj.CODIGO",
            "valorPadrao": null,
            "tipoAlinhamento": "ESQUERDA",
            "tipoEnum": null,
            "operacaoPadrao": null,
            "valor": "obj.CODIGO",
            "tipo": "INTEGER",
            "criadoEm": 21427887423662,
            "dinamico": false,
            "tipoOrdenacao": null,
            "obrigatorio": false,
            "descricao": "Código",
            "totalizar": false
        },
        {
            "valorOrdenacao": "obj.DATADECRIACAO",
            "valorPadrao": null,
            "tipoAlinhamento": "ESQUERDA",
            "tipoEnum": null,
            "operacaoPadrao": null,
            "valor": "obj.DATADECRIACAO",
            "tipo": "DATE",
            "criadoEm": 21436506068608,
            "dinamico": false,
            "tipoOrdenacao": null,
            "obrigatorio": false,
            "descricao": "Data de criação",
            "totalizar": false
        },
        {
            "valorOrdenacao": "coalesce(pf.NOME, us.LOGIN)",
            "valorPadrao": null,
            "tipoAlinhamento": "ESQUERDA",
            "tipoEnum": null,
            "operacaoPadrao": null,
            "valor": "coalesce(pf.NOME, us.LOGIN)",
            "tipo": "STRING",
            "criadoEm": 21441332473393,
            "dinamico": false,
            "tipoOrdenacao": null,
            "obrigatorio": false,
            "descricao": "Solicitante",
            "totalizar": false
        },
        {
            "valorOrdenacao": "letb.CODIGO || ' - ' || to_char(letb.DATAEFETIVACAO, 'dd/MM/yyyy') || ' - ' || coalesce(pfLteb.NOME, usLetb.LOGIN)",
            "valorPadrao": null,
            "tipoAlinhamento": "ESQUERDA",
            "tipoEnum": null,
            "operacaoPadrao": null,
            "valor": "letb.CODIGO || ' - ' || to_char(letb.DATAEFETIVACAO, 'dd/MM/yyyy') || ' - ' || coalesce(pfLteb.NOME, usLetb.LOGIN)",
            "tipo": "STRING",
            "criadoEm": 21445700607455,
            "dinamico": false,
            "tipoOrdenacao": null,
            "obrigatorio": false,
            "descricao": "Efetivação de Transferência",
            "totalizar": false
        },
        {
            "valorOrdenacao": "obj.SITUACAO",
            "valorPadrao": null,
            "tipoAlinhamento": "ESQUERDA",
            "tipoEnum": "br.com.webpublico.enums.SituacaoEventoBem",
            "operacaoPadrao": null,
            "valor": "obj.SITUACAO",
            "tipo": "ENUM",
            "criadoEm": 21449751265639,
            "dinamico": false,
            "tipoOrdenacao": null,
            "obrigatorio": false,
            "descricao": "Situação",
            "totalizar": false
        }
    ],
    "actionsTabela": [
        {
            "isDownload": false,
            "title": "Clique para visualizar este registro.",
            "alinhamento": "ESQUERDA",
            "download": false,
            "descricao": null,
            "icone": "ui-icon-search",
            "href": "../ver/$identificador/"
        },
        {
            "isDownload": false,
            "title": "Clique para ver o histórico deste registro.",
            "alinhamento": "DIREITA",
            "download": false,
            "descricao": null,
            "icone": "ui-icon-clock",
            "href": "/auditoria/listar-por-entidade/$identificador/SOLICITACAO_ESTORNO_TRANSFERENCIA/"
        }
    ],
    "filtros": []
}
