{
    "totalizadores": {},
    "paginaAtual": 0,
    "pesquisaveis": [
        {
            "tipo": "STRING",
            "dinamico": false,
            "select": null,
            "obrigatorio": false,
            "tipoEnum": null,
            "totalizar": false,
            "valor": "vs.placa",
            "tipoOrdenacao": null,
            "operacaoPadrao": "LIKE",
            "valorOrdenacao": null,
            "descricao": "Placa",
            "tipoAlinhamento": "ESQUERDA",
            "criadoEm": 253059955493000,
            "ordem": 0,
            "valorPadrao": ""
        },
        {
            "tipo": "STRING",
            "dinamico": false,
            "select": null,
            "obrigatorio": false,
            "tipoEnum": null,
            "totalizar": false,
            "valor": "M.DESCRICAO",
            "tipoOrdenacao": null,
            "operacaoPadrao": "LIKE",
            "valorOrdenacao": null,
            "descricao": "Marca",
            "tipoAlinhamento": "ESQUERDA",
            "criadoEm": 253078007724800,
            "ordem": 1,
            "valorPadrao": ""
        },
        {
            "tipo": "STRING",
            "dinamico": false,
            "select": null,
            "obrigatorio": false,
            "tipoEnum": null,
            "totalizar": false,
            "valor": "vs.modelo",
            "tipoOrdenacao": null,
            "operacaoPadrao": "LIKE",
            "valorOrdenacao": null,
            "descricao": "Modelo",
            "tipoAlinhamento": "ESQUERDA",
            "criadoEm": 253222065375300,
            "ordem": 2,
            "valorPadrao": ""
        },
        {
            "tipo": "STRING",
            "dinamico": false,
            "select": null,
            "obrigatorio": false,
            "tipoEnum": null,
            "totalizar": false,
            "valor": "cor.descricao",
            "tipoOrdenacao": null,
            "operacaoPadrao": "LIKE",
            "valorOrdenacao": null,
            "descricao": "Cor",
            "tipoAlinhamento": "ESQUERDA",
            "criadoEm": 253243563506300,
            "ordem": 3,
            "valorPadrao": ""
        },
        {
            "tipo": "INTEGER",
            "dinamico": false,
            "select": null,
            "obrigatorio": false,
            "tipoEnum": null,
            "totalizar": false,
            "valor": "vs.anofabricacao",
            "tipoOrdenacao": null,
            "operacaoPadrao": "IGUAL",
            "valorOrdenacao": null,
            "descricao": "Ano de Fabrica  o",
            "tipoAlinhamento": "ESQUERDA",
            "criadoEm": 253274227936900,
            "ordem": 4,
            "valorPadrao": ""
        },
        {
            "tipo": "INTEGER",
            "dinamico": false,
            "select": null,
            "obrigatorio": false,
            "tipoEnum": null,
            "totalizar": false,
            "valor": "VS.CAPACIDADEPASSAGEIROS",
            "tipoOrdenacao": null,
            "operacaoPadrao": "IGUAL",
            "valorOrdenacao": null,
            "descricao": "Capacidade de Passageiros",
            "tipoAlinhamento": "ESQUERDA",
            "criadoEm": 253305627693600,
            "ordem": 5,
            "valorPadrao": ""
        },
        {
            "tipo": "BOOLEAN",
            "dinamico": false,
            "select": null,
            "obrigatorio": false,
            "tipoEnum": null,
            "totalizar": false,
            "valor": "vs.ativo",
            "tipoOrdenacao": null,
            "operacaoPadrao": "IGUAL",
            "valorOrdenacao": null,
            "descricao": "Ativo?",
            "tipoAlinhamento": "ESQUERDA",
            "criadoEm": 253325996681700,
            "ordem": 6,
            "valorPadrao": null
        }
    ],
    "actionsHeader": [{
        "isDownload": false,
        "download": false,
        "icone": "ui-icon-plus",
        "style": "",
        "href": "../novo/",
        "title": "Clique para criar um novo registro.",
        "alinhamento": "ESQUERDA",
        "descricao": "Novo"
    }],
    "chave": "VEICULO_SAUD",
    "distinct": false,
    "tabelaveis": [
        {
            "tipo": "STRING",
            "dinamico": false,
            "select": null,
            "obrigatorio": false,
            "tipoEnum": null,
            "totalizar": false,
            "valor": "VS.PLACA",
            "tipoOrdenacao": null,
            "operacaoPadrao": null,
            "valorOrdenacao": "VS.PLACA",
            "descricao": "Placa",
            "tipoAlinhamento": "ESQUERDA",
            "criadoEm": 252728530592300,
            "ordem": 0,
            "valorPadrao": null
        },
        {
            "tipo": "STRING",
            "dinamico": false,
            "select": null,
            "obrigatorio": false,
            "tipoEnum": null,
            "totalizar": false,
            "valor": "M.DESCRICAO||' '||VS.MODELO||' '||COR.DESCRICAO||' (Ano: '||TO_CHAR(vs.ANOFABRICACAO)||')'",
            "tipoOrdenacao": null,
            "operacaoPadrao": null,
            "valorOrdenacao": "M.DESCRICAO||' '||VS.MODELO||' '||COR.DESCRICAO||' (Ano: '||TO_CHAR(vs.ANOFABRICACAO)||')'",
            "descricao": "Veiculo",
            "tipoAlinhamento": "ESQUERDA",
            "criadoEm": 252746573780600,
            "ordem": 1,
            "valorPadrao": null
        },
        {
            "tipo": "STRING",
            "dinamico": false,
            "select": null,
            "obrigatorio": false,
            "tipoEnum": null,
            "totalizar": false,
            "valor": "VS.CAPACIDADEPASSAGEIROS",
            "tipoOrdenacao": null,
            "operacaoPadrao": null,
            "valorOrdenacao": "VS.CAPACIDADEPASSAGEIROS",
            "descricao": "Capacidade de Passageiros",
            "tipoAlinhamento": "ESQUERDA",
            "criadoEm": 252755861805200,
            "ordem": 2,
            "valorPadrao": null
        },
        {
            "tipo": "STRING",
            "dinamico": false,
            "select": null,
            "obrigatorio": false,
            "tipoEnum": null,
            "totalizar": false,
            "valor": "pf.nome || ' - ' || formatacpfcnpj(pf.cpf)",
            "tipoOrdenacao": null,
            "operacaoPadrao": null,
            "valorOrdenacao": "pf.nome || ' - ' || formatacpfcnpj(pf.cpf)",
            "descricao": "Motorista",
            "tipoAlinhamento": "ESQUERDA",
            "criadoEm": 252766467192500,
            "ordem": 4,
            "valorPadrao": null
        },
        {
            "tipo": "BOOLEAN",
            "dinamico": false,
            "select": null,
            "obrigatorio": false,
            "tipoEnum": null,
            "totalizar": false,
            "valor": "vs.ativo",
            "tipoOrdenacao": null,
            "operacaoPadrao": null,
            "valorOrdenacao": "vs.ativo",
            "descricao": "Ativo?",
            "tipoAlinhamento": "ESQUERDA",
            "criadoEm": 252756438120000,
            "ordem": 3,
            "valorPadrao": null
        }
    ],
    "groupBy": "",
    "actionsTabela": [
        {
            "isDownload": false,
            "download": false,
            "icone": "ui-icon-search",
            "style": "",
            "href": "../ver/$identificador/",
            "title": "Clique para visualizar este registro.",
            "alinhamento": "ESQUERDA",
            "descricao": null
        },
        {
            "isDownload": false,
            "download": false,
            "icone": "ui-icon-pencil",
            "style": "",
            "href": "../editar/$identificador/",
            "title": "Clique para editar este registro.",
            "alinhamento": "ESQUERDA",
            "descricao": null
        },
        {
            "isDownload": false,
            "download": false,
            "icone": "ui-icon-clock",
            "style": "",
            "href": "/auditoria/listar-por-entidade/$identificador/VEICULO_SAUD/",
            "title": "Clique para ver o hist rico deste registro.",
            "alinhamento": "DIREITA",
            "descricao": null
        }
    ],
    "totalRegistros": 0,
    "nomeTela": "Veiculos do SAUD",
    "resultados": [],
    "registroPorPagina": 10,
    "from": "FROM VEICULOSAUD VS\r\nINNER JOIN MOTORISTASAUD MS ON VS.MOTORISTASAUD_ID = MS.ID\r\nINNER JOIN PESSOAFISICA PF ON MS.PESSOAFISICA_ID = PF.ID\r\nINNER JOIN MARCA M ON VS.MARCA_ID = M.ID\r\nINNER JOIN COR ON VS.COR_ID = COR.ID",
    "filtros": [],
    "identificador": {
        "tipo": null,
        "dinamico": false,
        "select": null,
        "obrigatorio": false,
        "tipoEnum": null,
        "totalizar": false,
        "valor": "vs.id",
        "tipoOrdenacao": null,
        "operacaoPadrao": null,
        "valorOrdenacao": null,
        "descricao": null,
        "tipoAlinhamento": "ESQUERDA",
        "criadoEm": 252705115749300,
        "ordem": null,
        "valorPadrao": null
    }
}