{
  "totalizadores": {},
  "paginaAtual": 0,
  "pesquisaveis": [
    {
      "tipo": "DATE",
      "dinamico": false,
      "select": null,
      "obrigatorio": false,
      "tipoEnum": null,
      "totalizar": false,
      "valor": "obj.INICIOVIGENCIA",
      "tipoOrdenacao": null,
      "operacaoPadrao": null,
      "valorOrdenacao": "obj.INICIOVIGENCIA",
      "descricao": "Início de Vigência",
      "tipoAlinhamento": "ESQUERDA",
      "criadoEm": 32717879099872,
      "ordem": null,
      "valorPadrao": null
    },
    {
      "tipo": "DATE",
      "dinamico": false,
      "select": null,
      "obrigatorio": false,
      "tipoEnum": null,
      "totalizar": false,
      "valor": "obj.FINALVIGENCIA",
      "tipoOrdenacao": null,
      "operacaoPadrao": null,
      "valorOrdenacao": "obj.FINALVIGENCIA",
      "descricao": "Final de Vigência",
      "tipoAlinhamento": "ESQUERDA",
      "criadoEm": 32718761082990,
      "ordem": null,
      "valorPadrao": null
    },
    {
      "tipo": "STRING",
      "dinamico": false,
      "select": null,
      "obrigatorio": false,
      "tipoEnum": null,
      "totalizar": false,
      "valor": "goc.CODIGO",
      "tipoOrdenacao": null,
      "operacaoPadrao": null,
      "valorOrdenacao": null,
      "descricao": "Grupo de Objeto de Compra.Código",
      "tipoAlinhamento": "ESQUERDA",
      "criadoEm": 32728701984672,
      "ordem": null,
      "valorPadrao": ""
    },
    {
      "tipo": "STRING",
      "dinamico": false,
      "select": null,
      "obrigatorio": false,
      "tipoEnum": null,
      "totalizar": false,
      "valor": "goc.DESCRICAO",
      "tipoOrdenacao": null,
      "operacaoPadrao": null,
      "valorOrdenacao": null,
      "descricao": "Grupo de Objeto de Compra.Descrição",
      "tipoAlinhamento": "ESQUERDA",
      "criadoEm": 32736131298144,
      "ordem": null,
      "valorPadrao": ""
    },
    {
      "tipo": "STRING",
      "dinamico": false,
      "select": null,
      "obrigatorio": false,
      "tipoEnum": null,
      "totalizar": false,
      "valor": "gm.CODIGO",
      "tipoOrdenacao": null,
      "operacaoPadrao": null,
      "valorOrdenacao": null,
      "descricao": "Grupo de Materiais.Código",
      "tipoAlinhamento": "ESQUERDA",
      "criadoEm": 32742769935758,
      "ordem": null,
      "valorPadrao": ""
    },
    {
      "tipo": "STRING",
      "dinamico": false,
      "select": null,
      "obrigatorio": false,
      "tipoEnum": null,
      "totalizar": false,
      "valor": "gm.DESCRICAO",
      "tipoOrdenacao": null,
      "operacaoPadrao": null,
      "valorOrdenacao": null,
      "descricao": "Grupo de Materiais.Descrição",
      "tipoAlinhamento": "ESQUERDA",
      "criadoEm": 32747671856035,
      "ordem": null,
      "valorPadrao": ""
    },
    {
      "tipo": "ENUM",
      "dinamico": false,
      "select": null,
      "obrigatorio": false,
      "tipoEnum": "br.com.webpublico.enums.SituacaoCadastralContabil",
      "totalizar": false,
      "valor": "gm.ATIVOINATIVO",
      "tipoOrdenacao": null,
      "operacaoPadrao": null,
      "valorOrdenacao": null,
      "descricao": "Grupo de Materiais.Situação",
      "tipoAlinhamento": "ESQUERDA",
      "criadoEm": 32753749388467,
      "ordem": null,
      "valorPadrao": null
    },
    {
      "tipo": "STRING",
      "dinamico": false,
      "select": null,
      "obrigatorio": false,
      "tipoEnum": null,
      "totalizar": false,
      "valor": "c.codigo",
      "tipoOrdenacao": null,
      "operacaoPadrao": "LIKE",
      "valorOrdenacao": null,
      "descricao": "Conta Despesa.Código",
      "tipoAlinhamento": "ESQUERDA",
      "criadoEm": 14257207788909,
      "ordem": 7,
      "valorPadrao": ""
    },
    {
      "tipo": "STRING",
      "dinamico": false,
      "select": null,
      "obrigatorio": false,
      "tipoEnum": null,
      "totalizar": false,
      "valor": "c.descricao",
      "tipoOrdenacao": null,
      "operacaoPadrao": "LIKE",
      "valorOrdenacao": null,
      "descricao": "Conta Despesa.Descrição",
      "tipoAlinhamento": "ESQUERDA",
      "criadoEm": 14280927241152,
      "ordem": 8,
      "valorPadrao": ""
    }
  ],
  "actionsHeader": [{
    "isDownload": false,
    "download": false,
    "icone": "ui-icon-plus",
    "style": "",
    "href": "../novo/",
    "title": "Clique para criar um novo registro.",
    "alinhamento": "ESQUERDA",
    "descricao": "Novo"
  }],
  "chave": "ASSOCIACAO_GRUPO_OBJETO_COMPRA_GRUPO_MATERIAL",
  "distinct": false,
  "tabelaveis": [
    {
      "tipo": "DATE",
      "dinamico": false,
      "select": null,
      "obrigatorio": false,
      "tipoEnum": null,
      "totalizar": false,
      "valor": "obj.INICIOVIGENCIA",
      "tipoOrdenacao": null,
      "operacaoPadrao": null,
      "valorOrdenacao": "obj.INICIOVIGENCIA",
      "descricao": "Início de Vigência",
      "tipoAlinhamento": "ESQUERDA",
      "criadoEm": 32664400517094,
      "ordem": null,
      "valorPadrao": null
    },
    {
      "tipo": "DATE",
      "dinamico": false,
      "select": null,
      "obrigatorio": false,
      "tipoEnum": null,
      "totalizar": false,
      "valor": "obj.FINALVIGENCIA",
      "tipoOrdenacao": null,
      "operacaoPadrao": null,
      "valorOrdenacao": "obj.FINALVIGENCIA",
      "descricao": "Final de Vigência",
      "tipoAlinhamento": "ESQUERDA",
      "criadoEm": 32670841664228,
      "ordem": null,
      "valorPadrao": null
    },
    {
      "tipo": "STRING",
      "dinamico": false,
      "select": null,
      "obrigatorio": false,
      "tipoEnum": null,
      "totalizar": false,
      "valor": "goc.CODIGO || ' - ' || goc.DESCRICAO",
      "tipoOrdenacao": null,
      "operacaoPadrao": null,
      "valorOrdenacao": "goc.CODIGO || ' - ' || goc.DESCRICAO",
      "descricao": "Grupo de Objeto de Compra",
      "tipoAlinhamento": "ESQUERDA",
      "criadoEm": 32680260944646,
      "ordem": null,
      "valorPadrao": null
    },
    {
      "tipo": "STRING",
      "dinamico": false,
      "select": null,
      "obrigatorio": false,
      "tipoEnum": null,
      "totalizar": false,
      "valor": "gm.CODIGO || ' - ' || gm.DESCRICAO",
      "tipoOrdenacao": null,
      "operacaoPadrao": null,
      "valorOrdenacao": "gm.CODIGO || ' - ' || gm.DESCRICAO",
      "descricao": "Grupo de Materiais",
      "tipoAlinhamento": "ESQUERDA",
      "criadoEm": 32685705516205,
      "ordem": null,
      "valorPadrao": null
    },
    {
      "tipo": "STRING",
      "dinamico": false,
      "select": null,
      "obrigatorio": false,
      "tipoEnum": null,
      "totalizar": false,
      "valor": "case when c.codigo is not null and c.descricao is not null then c.codigo || ' - ' || c.descricao else '' end",
      "tipoOrdenacao": null,
      "operacaoPadrao": null,
      "valorOrdenacao": "case when c.codigo is not null and c.descricao is not null then c.codigo || ' - ' || c.descricao else '' end",
      "descricao": "Contas",
      "tipoAlinhamento": "ESQUERDA",
      "criadoEm": 14305704321978,
      "ordem": 4,
      "valorPadrao": null
    }
  ],
  "groupBy": "group by obj.id, obj.iniciovigencia,obj.finalvigencia,goc.codigo, goc.descricao,gm.codigo, gm.descricao,c.codigo, c.descricao",
  "actionsTabela": [
    {
      "isDownload": false,
      "download": false,
      "icone": "ui-icon-search",
      "style": "",
      "href": "../ver/$identificador/",
      "title": "Clique para visualizar este registro.",
      "alinhamento": "ESQUERDA",
      "descricao": null
    },
    {
      "isDownload": false,
      "download": false,
      "icone": "ui-icon-pencil",
      "style": "",
      "href": "../editar/$identificador/",
      "title": "Clique para editar este registro.",
      "alinhamento": "ESQUERDA",
      "descricao": null
    },
    {
      "isDownload": false,
      "download": false,
      "icone": "ui-icon-clock",
      "style": "",
      "href": "/auditoria/listar-por-entidade/$identificador/ASSOCIACAO_GRUPO_OBJETO_COMPRA_GRUPO_MATERIAL/",
      "title": "Clique para ver o histórico deste registro.",
      "alinhamento": "DIREITA",
      "descricao": null
    }
  ],
  "totalRegistros": 5189,
  "nomeTela": "Associação Grupo de Objeto de Compra e Grupo de Materiais",
  "resultados": [],
  "registroPorPagina": 10,
  "from": "\tfrom associacaogruobjcomgrumat obj\r\n    inner join grupoobjetocompra goc on goc.id = obj.grupoobjetocompra_id\r\n    inner join grupomaterial gm on gm.id = obj.grupomaterial_id\r\n    left join objetocompra oc on oc.grupoobjetocompra_id = goc.id\r\n    left join bem bem on bem.objetocompra_id = oc.id\r\n    left join eventobem ev on ev.bem_id = bem.id\r\n\tleft join estadobem est on est.id = ev.estadoresultante_id\r\n\tleft join grupobem gb on gb.id = est.grupobem_id\r\n    left join configdespesabens config on config.grupobem_id = gb.id\r\n\tleft join contadespesa cd on config.contadespesa_id = cd.id\r\n\tleft join conta c on c.id = cd.id",
  "filtros": [{
    "field": null,
    "operadorLogico": "AND",
    "operacao": null,
    "valor": null
  }],
  "identificador": {
    "tipo": null,
    "dinamico": false,
    "select": null,
    "obrigatorio": false,
    "tipoEnum": null,
    "totalizar": false,
    "valor": "obj.id",
    "tipoOrdenacao": null,
    "operacaoPadrao": null,
    "valorOrdenacao": null,
    "descricao": null,
    "tipoAlinhamento": "ESQUERDA",
    "criadoEm": 32205573280448,
    "ordem": null,
    "valorPadrao": null
  }
}
