{
    "totalizadores": {},
    "paginaAtual": 0,
    "pesquisaveis": [
        {
            "tipo": "STRING",
            "dinamico": false,
            "select": null,
            "obrigatorio": false,
            "tipoEnum": null,
            "totalizar": false,
            "valor": "mat.MATRICULA",
            "tipoOrdenacao": null,
            "operacaoPadrao": "LIKE",
            "valorOrdenacao": null,
            "descricao": "Matricula",
            "tipoAlinhamento": "ESQUERDA",
            "criadoEm": 12510822131613232,
            "ordem": 0,
            "valorPadrao": ""
        },
        {
            "tipo": "INTEGER",
            "dinamico": false,
            "select": null,
            "obrigatorio": false,
            "tipoEnum": null,
            "totalizar": false,
            "valor": "vinculo.NUMERO",
            "tipoOrdenacao": null,
            "operacaoPadrao": "IGUAL",
            "valorOrdenacao": null,
            "descricao": "Contrato",
            "tipoAlinhamento": "ESQUERDA",
            "criadoEm": 12510827735973860,
            "ordem": 1,
            "valorPadrao": ""
        },
        {
            "tipo": "STRING",
            "dinamico": false,
            "select": null,
            "obrigatorio": false,
            "tipoEnum": null,
            "totalizar": false,
            "valor": "pf.nome",
            "tipoOrdenacao": null,
            "operacaoPadrao": "LIKE",
            "valorOrdenacao": null,
            "descricao": "Servidor",
            "tipoAlinhamento": "ESQUERDA",
            "criadoEm": 12510831730555640,
            "ordem": 2,
            "valorPadrao": ""
        },
        {
            "tipo": "DATE",
            "dinamico": false,
            "select": null,
            "obrigatorio": false,
            "tipoEnum": null,
            "totalizar": false,
            "valor": "risco.INICIO",
            "tipoOrdenacao": null,
            "operacaoPadrao": "IGUAL",
            "valorOrdenacao": null,
            "descricao": "Inicio",
            "tipoAlinhamento": "ESQUERDA",
            "criadoEm": 12510835816899487,
            "ordem": 3,
            "valorPadrao": null
        },
        {
            "tipo": "DATE",
            "dinamico": false,
            "select": null,
            "obrigatorio": false,
            "tipoEnum": null,
            "totalizar": false,
            "valor": "risco.FIM",
            "tipoOrdenacao": null,
            "operacaoPadrao": "IGUAL",
            "valorOrdenacao": null,
            "descricao": "Fim",
            "tipoAlinhamento": "ESQUERDA",
            "criadoEm": 12510841155609026,
            "ordem": 4,
            "valorPadrao": null
        }
    ],
    "actionsHeader": [{
        "isDownload": false,
        "download": false,
        "icone": "ui-icon-plus",
        "style": "",
        "href": "../novo/",
        "title": "Clique para criar um novo registro.",
        "alinhamento": "ESQUERDA",
        "descricao": "Novo"
    }],
    "chave": "RISCO_OCUPACIONAL",
    "distinct": false,
    "tabelaveis": [
        {
            "tipo": "DATE",
            "dinamico": false,
            "select": null,
            "obrigatorio": false,
            "tipoEnum": null,
            "totalizar": false,
            "valor": "risco.INICIO",
            "tipoOrdenacao": null,
            "operacaoPadrao": null,
            "valorOrdenacao": "risco.INICIO",
            "descricao": "Inicio",
            "tipoAlinhamento": "ESQUERDA",
            "criadoEm": 12510933355004365,
            "ordem": 0,
            "valorPadrao": null
        },
        {
            "tipo": "DATE",
            "dinamico": false,
            "select": null,
            "obrigatorio": false,
            "tipoEnum": null,
            "totalizar": false,
            "valor": "risco.FIM",
            "tipoOrdenacao": null,
            "operacaoPadrao": null,
            "valorOrdenacao": "risco.FIM",
            "descricao": "Fim",
            "tipoAlinhamento": "ESQUERDA",
            "criadoEm": 12510936002894747,
            "ordem": 1,
            "valorPadrao": null
        },
        {
            "tipo": "STRING",
            "dinamico": false,
            "select": null,
            "obrigatorio": false,
            "tipoEnum": null,
            "totalizar": false,
            "valor": "mat.MATRICULA || '/' || vinculo.NUMERO || ' ' || pf.nome",
            "tipoOrdenacao": null,
            "operacaoPadrao": null,
            "valorOrdenacao": "mat.MATRICULA || '/' || vinculo.NUMERO || ' ' || pf.nome",
            "descricao": "Servidor",
            "tipoAlinhamento": "ESQUERDA",
            "criadoEm": 12510939198339759,
            "ordem": 2,
            "valorPadrao": null
        },
        {
            "tipo": "STRING",
            "dinamico": false,
            "select": null,
            "obrigatorio": false,
            "tipoEnum": null,
            "totalizar": false,
            "valor": " risco.DESCRICAOATIVIDADE",
            "tipoOrdenacao": null,
            "operacaoPadrao": null,
            "valorOrdenacao": " risco.DESCRICAOATIVIDADE",
            "descricao": "Descrição Atividade",
            "tipoAlinhamento": "ESQUERDA",
            "criadoEm": 12510973973412867,
            "ordem": 3,
            "valorPadrao": null
        },
        {
            "tipo": "STRING",
            "dinamico": false,
            "select": null,
            "obrigatorio": false,
            "tipoEnum": null,
            "totalizar": false,
            "valor": "risco.DESCRICAOSETOR",
            "tipoOrdenacao": null,
            "operacaoPadrao": null,
            "valorOrdenacao": "risco.DESCRICAOSETOR",
            "descricao": "Descrição Setor",
            "tipoAlinhamento": "ESQUERDA",
            "criadoEm": 12510976374630256,
            "ordem": 4,
            "valorPadrao": null
        }
    ],
    "groupBy": "",
    "actionsTabela": [
        {
            "isDownload": false,
            "download": false,
            "icone": "ui-icon-search",
            "style": "",
            "href": "../ver/$identificador/",
            "title": "Clique para visualizar este registro.",
            "alinhamento": "ESQUERDA",
            "descricao": null
        },
        {
            "isDownload": false,
            "download": false,
            "icone": "ui-icon-pencil",
            "style": "",
            "href": "../editar/$identificador/",
            "title": "Clique para editar este registro.",
            "alinhamento": "ESQUERDA",
            "descricao": null
        },
        {
            "isDownload": false,
            "download": false,
            "icone": "ui-icon-clock",
            "style": "",
            "href": "/auditoria/listar-por-entidade/$identificador/RiscoOcupacional/",
            "title": "Clique para ver o histórico deste registro.",
            "alinhamento": "DIREITA",
            "descricao": null
        }
    ],
    "totalRegistros": 0,
    "nomeTela": "Risco Ocupacional",
    "resultados": [],
    "registroPorPagina": 10,
    "from": "from RISCOOCUPACIONAL risco\r\ninner join vinculofp vinculo on risco.VINCULOFP_ID = vinculo.ID\r\ninner join matriculafp mat on vinculo.MATRICULAFP_ID = mat.ID\r\ninner join pessoafisica pf on mat.PESSOA_ID = pf.ID",
    "filtros": [],
    "identificador": {
        "tipo": null,
        "dinamico": false,
        "select": null,
        "obrigatorio": false,
        "tipoEnum": null,
        "totalizar": false,
        "valor": "risco.id",
        "tipoOrdenacao": null,
        "operacaoPadrao": null,
        "valorOrdenacao": null,
        "descricao": null,
        "tipoAlinhamento": "ESQUERDA",
        "criadoEm": 12510763719542715,
        "ordem": null,
        "valorPadrao": null
    }
}