{
  "resultados": [],
  "paginaAtual": 0,
  "nomeTela": "Tipo de Provimento",
  "actionsHeader": [
    {
      "isDownload": false,
      "title": "Clique para criar um novo registro.",
      "style": "",
      "alinhamento": "ESQUERDA",
      "download": false,
      "descricao": "Novo",
      "icone": "ui-icon-plus",
      "href": "../novo/"
    }
  ],
  "totalRegistros": 38,
  "totalizadores": {},
  "chave": "TIPO_PROVIMENTO",
  "pesquisaveis": [
    {
      "valorOrdenacao": null,
      "valorPadrao": "",
      "tipoAlinhamento": "ESQUERDA",
      "tipoEnum": null,
      "operacaoPadrao": "IGUAL",
      "valor": "codigo",
      "tipo": "INTEGER",
      "criadoEm": 316889807541624,
      "dinamico": false,
      "tipoOrdenacao": null,
      "obrigatorio": false,
      "descricao": "Código",
      "totalizar": false
    },
    {
      "valorOrdenacao": null,
      "valorPadrao": "",
      "tipoAlinhamento": "ESQUERDA",
      "tipoEnum": null,
      "operacaoPadrao": "LIKE",
      "valor": "descricao",
      "tipo": "STRING",
      "criadoEm": 316907638066711,
      "dinamico": false,
      "tipoOrdenacao": null,
      "obrigatorio": false,
      "descricao": "Descrição",
      "totalizar": false
    }
  ],
  "from": "from TipoProvimento",
  "distinct": false,
  "groupBy": "",
  "registroPorPagina": 10,
  "identificador": {
    "valorOrdenacao": null,
    "valorPadrao": null,
    "tipoAlinhamento": "ESQUERDA",
    "tipoEnum": null,
    "operacaoPadrao": null,
    "valor": "id",
    "tipo": null,
    "criadoEm": 316869603246447,
    "dinamico": false,
    "tipoOrdenacao": null,
    "obrigatorio": false,
    "descricao": null,
    "totalizar": false
  },
  "tabelaveis": [
    {
      "valorOrdenacao": "codigo",
      "valorPadrao": null,
      "tipoAlinhamento": "ESQUERDA",
      "tipoEnum": null,
      "operacaoPadrao": null,
      "valor": "codigo",
      "tipo": "INTEGER",
      "criadoEm": 316923360464858,
      "dinamico": false,
      "tipoOrdenacao": null,
      "obrigatorio": false,
      "descricao": "Código",
      "totalizar": false
    },
    {
      "valorOrdenacao": "descricao",
      "valorPadrao": null,
      "tipoAlinhamento": "ESQUERDA",
      "tipoEnum": null,
      "operacaoPadrao": null,
      "valor": "descricao",
      "tipo": "STRING",
      "criadoEm": 316924108728053,
      "dinamico": false,
      "tipoOrdenacao": null,
      "obrigatorio": false,
      "descricao": "Descrição",
      "totalizar": false
    }
  ],
  "actionsTabela": [
    {
      "isDownload": false,
      "title": "Clique para visualizar este registro.",
      "style": "",
      "alinhamento": "ESQUERDA",
      "download": false,
      "descricao": null,
      "icone": "ui-icon-search",
      "href": "../ver/$identificador/"
    },
    {
      "isDownload": false,
      "title": "Clique para editar este registro.",
      "style": "",
      "alinhamento": "ESQUERDA",
      "download": false,
      "descricao": null,
      "icone": "ui-icon-pencil",
      "href": "../editar/$identificador/"
    },
    {
      "isDownload": false,
      "title": "Clique para ver o histórico deste registro.",
      "style": "",
      "alinhamento": "DIREITA",
      "download": false,
      "descricao": null,
      "icone": "ui-icon-clock",
      "href": "/auditoria/listar-por-entidade/$identificador/TipoProvimento/"
    }
  ],
  "filtros": []
}
