{
    "resultados": [],
    "paginaAtual": 0,
    "nomeTela": "Tributo",
    "actionsHeader": [{
        "isDownload": false,
        "title": "Clique para criar um novo registro.",
        "alinhamento": "ESQUERDA",
        "download": false,
        "descricao": "Novo",
        "icone": "ui-icon-plus",
        "href": "../novo/"
    }],
    "totalRegistros": 511,
    "totalizadores": {},
    "chave": "TRIBUTO",
    "pesquisaveis": [
        {
            "valorOrdenacao": null,
            "valorPadrao": "",
            "tipoAlinhamento": "ESQUERDA",
            "tipoEnum": null,
            "operacaoPadrao": "IGUAL",
            "valor": "T.CODIGO",
            "tipo": "INTEGER",
            "criadoEm": 3357014678900,
            "dinamico": false,
            "tipoOrdenacao": null,
            "obrigatorio": false,
            "descricao": "Código",
            "totalizar": false
        },
        {
            "valorOrdenacao": null,
            "valorPadrao": "",
            "tipoAlinhamento": "ESQUERDA",
            "tipoEnum": null,
            "operacaoPadrao": "LIKE",
            "valor": "T.DESCRICAO",
            "tipo": "STRING",
            "criadoEm": 3357931950000,
            "dinamico": false,
            "tipoOrdenacao": null,
            "obrigatorio": false,
            "descricao": "Descrição",
            "totalizar": false
        },
        {
            "valorOrdenacao": null,
            "valorPadrao": null,
            "tipoAlinhamento": "ESQUERDA",
            "tipoEnum": "br.com.webpublico.entidades.Tributo$TipoTributo",
            "operacaoPadrao": "IGUAL",
            "valor": "T.TIPOTRIBUTO",
            "tipo": "ENUM",
            "criadoEm": 3359390905200,
            "dinamico": false,
            "tipoOrdenacao": null,
            "obrigatorio": false,
            "descricao": "Tipo de Tributo",
            "totalizar": false
        }
    ],
    "from": "FROM TRIBUTO T",
    "distinct": false,
    "groupBy": "",
    "registroPorPagina": 10,
    "identificador": {
        "valorOrdenacao": null,
        "valorPadrao": null,
        "tipoAlinhamento": "ESQUERDA",
        "tipoEnum": null,
        "operacaoPadrao": null,
        "valor": "t.id",
        "tipo": null,
        "criadoEm": 3347633013400,
        "dinamico": false,
        "tipoOrdenacao": null,
        "obrigatorio": false,
        "descricao": null,
        "totalizar": false
    },
    "tabelaveis": [
        {
            "valorOrdenacao": "T.CODIGO",
            "valorPadrao": null,
            "tipoAlinhamento": "ESQUERDA",
            "tipoEnum": null,
            "operacaoPadrao": null,
            "valor": "T.CODIGO",
            "tipo": "INTEGER",
            "criadoEm": 3910624952800,
            "dinamico": false,
            "tipoOrdenacao": null,
            "obrigatorio": false,
            "descricao": "Código",
            "totalizar": false
        },
        {
            "valorOrdenacao": "T.DESCRICAO",
            "valorPadrao": null,
            "tipoAlinhamento": "ESQUERDA",
            "tipoEnum": null,
            "operacaoPadrao": null,
            "valor": "T.DESCRICAO",
            "tipo": "STRING",
            "criadoEm": 3911470813600,
            "dinamico": false,
            "tipoOrdenacao": null,
            "obrigatorio": false,
            "descricao": "Descrição",
            "totalizar": false
        },
        {
            "valorOrdenacao": "T.TIPOTRIBUTO",
            "valorPadrao": null,
            "tipoAlinhamento": "ESQUERDA",
            "tipoEnum": "br.com.webpublico.entidades.Tributo$TipoTributo",
            "operacaoPadrao": null,
            "valor": "T.TIPOTRIBUTO",
            "tipo": "ENUM",
            "criadoEm": 3912342517400,
            "dinamico": false,
            "tipoOrdenacao": null,
            "obrigatorio": false,
            "descricao": "Tipo de Tributo",
            "totalizar": false
        }
    ],
    "actionsTabela": [
        {
            "isDownload": false,
            "title": "Clique para visualizar este registro.",
            "alinhamento": "ESQUERDA",
            "download": false,
            "descricao": null,
            "icone": "ui-icon-search",
            "href": "../ver/$identificador/"
        },
        {
            "isDownload": false,
            "title": "Clique para editar este registro.",
            "alinhamento": "ESQUERDA",
            "download": false,
            "descricao": null,
            "icone": "ui-icon-pencil",
            "href": "../editar/$identificador/"
        },
        {
            "isDownload": false,
            "title": "Clique para ver o histórico deste registro.",
            "alinhamento": "DIREITA",
            "download": false,
            "descricao": null,
            "icone": "ui-icon-clock",
            "href": "/auditoria/listar-por-entidade/$identificador/TRIBUTO/"
        }
    ],
    "filtros": []
}